covdata/__init__.py
covdata/cli.py
covdata/covidindia.py
covdata/districtdata.py
covdata/SERVER/__init__.py
covdata/SERVER/hideFile.py
covdata/SERVER/server.py
covdata/SERVER/static/analysis.js
covdata/SERVER/static/dashboard.js
covdata/SERVER/static/demo.js
covdata/SERVER/static/jquery.nice-select-analysis.js
covdata/SERVER/static/jquery.nice-select-demo.js
covdata/SERVER/static/jquery.nice-select-home.min.js
covdata/SERVER/static/jquery.nice-select-rank.js
covdata/SERVER/static/jquery.nice-select-state.js
covdata/SERVER/static/main.js
covdata/SERVER/static/nice-select-analysis.css
covdata/SERVER/static/nice-select-demo.css
covdata/SERVER/static/nice-select-home.css
covdata/SERVER/static/nice-select-home.css.dat
covdata/SERVER/static/nice-select-rank.css
covdata/SERVER/static/nice-select-state.css
covdata/SERVER/static/rank.js
covdata/SERVER/static/state.js
covdata/SERVER/static/style.css
covdata/SERVER/static/style_analysis.css
covdata/SERVER/static/style_dashboard.css
covdata/SERVER/static/style_demo.css
covdata/SERVER/static/style_rank.css
covdata/SERVER/static/style_state.css
covdata/SERVER/templates/index_analysis.html
covdata/SERVER/templates/index_dashboard.html
covdata/SERVER/templates/index_demo.html
covdata/SERVER/templates/index_home.html
covdata/SERVER/templates/index_rank.html
covdata/SERVER/templates/index_state.html
covdata-1.2.2.dist-info/LICENSE
covdata-1.2.2.dist-info/METADATA
covdata-1.2.2.dist-info/WHEEL
covdata-1.2.2.dist-info/entry_points.txt
covdata-1.2.2.dist-info/top_level.txt
covdata-1.2.2.dist-info/RECORD
