Metadata-Version: 2.1
Name: covdata
Version: 1.2.2
Summary: A package that can grab all data of Covid-19 cases in India
Home-page: https://github.com/kalyaniuniversity/covidindia
Author: Dripta senapati
Author-email: driptasenapati97@gmail.com
License: UNKNOWN
Platform: UNKNOWN
Classifier: Programming Language :: Python :: 3
Classifier: License :: OSI Approved :: MIT License
Classifier: Operating System :: OS Independent
Requires-Python: >=3.6
Requires-Dist: pandas (>=1.0.0)
Requires-Dist: numpy (>=1.18.1)
Requires-Dist: matplotlib (>=3.1.3)
Requires-Dist: datetime
Requires-Dist: flask (>=1.1.1)
Requires-Dist: Flask-CacheBuster (>=1.0.0)
